eosets/__init__.py
eosets/__meta__.py
eosets/env_vars.py
eosets/exceptions.py
eosets/mosaic.py
eosets/pair.py
eosets/series.py
eosets/set.py
eosets/utils.py
eosets-0.4.1.dist-info/licenses/LICENSE
eosets-0.4.1.dist-info/licenses/NOTICE
eosets-0.4.1.dist-info/METADATA
eosets-0.4.1.dist-info/WHEEL
eosets-0.4.1.dist-info/top_level.txt
eosets-0.4.1.dist-info/RECORD
