Metadata-Version: 2.4
Name: eosets
Version: 0.4.1
Summary: This library aims to simplify any process working with different sets of EO data handled by EOReader.
Author-email: ICube-SERTIT <dev-sertit@unistra.fr>
License: Apache 2.0
Project-URL: Bug_Tracker, https://github.com/sertit/eosets/issues
Project-URL: Documentation, https://eosets.readthedocs.io/latest/
Project-URL: Source_Code, https://github.com/sertit/eosets
Classifier: Development Status :: 4 - Beta
Classifier: Intended Audience :: Developers
Classifier: Intended Audience :: Science/Research
Classifier: Natural Language :: English
Classifier: License :: OSI Approved :: Apache Software License
Classifier: Programming Language :: Python :: 3
Classifier: Programming Language :: Python :: 3.9
Classifier: Programming Language :: Python :: 3.10
Classifier: Programming Language :: Python :: 3.11
Classifier: Programming Language :: Python :: 3.12
Classifier: Programming Language :: Python :: 3.13
Classifier: Programming Language :: Python :: 3.14
Classifier: Operating System :: OS Independent
Classifier: Topic :: Scientific/Engineering :: GIS
Classifier: Topic :: Software Development :: Libraries :: Python Modules
Requires-Python: >=3.10
License-File: LICENSE
License-File: NOTICE
Requires-Dist: lxml
Requires-Dist: h5netcdf
Requires-Dist: scipy
Requires-Dist: rasterio>=1.3.10
Requires-Dist: xarray>=2024.06.0
Requires-Dist: rioxarray>=0.15.0
Requires-Dist: odc-geo>=0.5.0
Requires-Dist: geopandas>=0.14.4
Requires-Dist: eoreader>=0.23.0
Requires-Dist: sertit[full]>=1.50.2
Dynamic: license-file
